{
    "_links": {
        "self": {
            "href": "https://eu.api.blizzard.com/data/wow/spell/105849?namespace=static-10.0.5_47621-eu"
        }
    },
    "id": 105849,
    "name": "Item - Rogue T13 2P Bonus (Tricks of the Trade)",
    "description": "After triggering Tricks of the Trade, your abilities cost 20% less energy for 6 sec.",
    "media": {
        "key": {
            "href": "https://eu.api.blizzard.com/data/wow/media/spell/105849?namespace=static-10.0.5_47621-eu"
        },
        "id": 105849
    }
}