{
    "_links": {
        "self": {
            "href": "https://eu.api.blizzard.com/data/wow/spell/216868?namespace=static-10.0.5_47621-eu"
        }
    },
    "id": 216868,
    "name": "Hallowed Ground",
    "description": "Your Consecration clears and suppresses all snare effects on allies within its area of effect.",
    "media": {
        "key": {
            "href": "https://eu.api.blizzard.com/data/wow/media/spell/216868?namespace=static-10.0.5_47621-eu"
        },
        "id": 216868
    }
}