{
    "_links": {
        "self": {
            "href": "https://eu.api.blizzard.com/data/wow/spell/363929?namespace=static-10.0.5_47621-eu"
        }
    },
    "id": 363929,
    "name": "[DND] Upgrades - Talent - Cooldown reduction",
    "description": "Increases the duration of Pocopoc's control of Automa to 5 min.\r\n\r\nReduces the cooldown of controlled Automa abilities by 5 sec.",
    "media": {
        "key": {
            "href": "https://eu.api.blizzard.com/data/wow/media/spell/363929?namespace=static-10.0.5_47621-eu"
        },
        "id": 363929
    }
}