{
    "_links": {
        "self": {
            "href": "https://eu.api.blizzard.com/data/wow/spell/385840?namespace=static-10.0.5_47621-eu"
        }
    },
    "id": 385840,
    "name": "Thunderlord",
    "description": "Increases the radius of Demoralizing Shout by 5 yards.\r\n\r\nEach enemy hit by Thunder Clap reduces the remaining cooldown on Demoralizing Shout by 1.0 sec, up to 3.0 sec.",
    "media": {
        "key": {
            "href": "https://eu.api.blizzard.com/data/wow/media/spell/385840?namespace=static-10.0.5_47621-eu"
        },
        "id": 385840
    }
}