{
    "_links": {
        "self": {
            "href": "https://eu.api.blizzard.com/data/wow/recipe/40742?namespace=static-10.0.5_47621-eu"
        }
    },
    "id": 40742,
    "name": "Banded Seaweave Breeches",
    "description": "Craft Banded Seaweave Breeches.",
    "media": {
        "key": {
            "href": "https://eu.api.blizzard.com/data/wow/media/recipe/40742?namespace=static-10.0.5_47621-eu"
        },
        "id": 40742
    },
    "alliance_crafted_item": {
        "key": {
            "href": "https://eu.api.blizzard.com/data/wow/item/168733?namespace=static-10.0.5_47621-eu"
        },
        "name": "Banded Seaweave Breeches",
        "id": 168733
    },
    "horde_crafted_item": {
        "key": {
            "href": "https://eu.api.blizzard.com/data/wow/item/168739?namespace=static-10.0.5_47621-eu"
        },
        "name": "Banded Seaweave Breeches",
        "id": 168739
    },
    "reagents": [
        {
            "reagent": {
                "key": {
                    "href": "https://eu.api.blizzard.com/data/wow/item/167738?namespace=static-10.0.5_47621-eu"
                },
                "name": "Gilded Seaweave",
                "id": 167738
            },
            "quantity": 115
        },
        {
            "reagent": {
                "key": {
                    "href": "https://eu.api.blizzard.com/data/wow/item/158378?namespace=static-10.0.5_47621-eu"
                },
                "name": "Embroidered Deep Sea Satin",
                "id": 158378
            },
            "quantity": 30
        },
        {
            "reagent": {
                "key": {
                    "href": "https://eu.api.blizzard.com/data/wow/item/159959?namespace=static-10.0.5_47621-eu"
                },
                "name": "Nylon Thread",
                "id": 159959
            },
            "quantity": 60
        },
        {
            "reagent": {
                "key": {
                    "href": "https://eu.api.blizzard.com/data/wow/item/152668?namespace=static-10.0.5_47621-eu"
                },
                "name": "Expulsom",
                "id": 152668
            },
            "quantity": 40
        }
    ],
    "rank": 1,
    "crafted_quantity": {
        "value": 1.0
    }
}