{
    "_links": {
        "self": {
            "href": "https://eu.api.blizzard.com/data/wow/recipe/19521?namespace=static-10.0.5_47621-eu"
        }
    },
    "id": 19521,
    "name": "Figurine - Twilight Serpent",
    "media": {
        "key": {
            "href": "https://eu.api.blizzard.com/data/wow/media/recipe/19521?namespace=static-10.0.5_47621-eu"
        },
        "id": 19521
    },
    "crafted_item": {
        "key": {
            "href": "https://eu.api.blizzard.com/data/wow/item/42395?namespace=static-10.0.5_47621-eu"
        },
        "name": "Figurine - Twilight Serpent",
        "id": 42395
    },
    "reagents": [
        {
            "reagent": {
                "key": {
                    "href": "https://eu.api.blizzard.com/data/wow/item/41163?namespace=static-10.0.5_47621-eu"
                },
                "name": "Titanium Bar",
                "id": 41163
            },
            "quantity": 2
        },
        {
            "reagent": {
                "key": {
                    "href": "https://eu.api.blizzard.com/data/wow/item/36927?namespace=static-10.0.5_47621-eu"
                },
                "name": "Twilight Opal",
                "id": 36927
            },
            "quantity": 2
        },
        {
            "reagent": {
                "key": {
                    "href": "https://eu.api.blizzard.com/data/wow/item/36930?namespace=static-10.0.5_47621-eu"
                },
                "name": "Monarch Topaz",
                "id": 36930
            },
            "quantity": 1
        }
    ],
    "crafted_quantity": {
        "value": 1.0
    },
    "modified_crafting_slots": [
        {
            "slot_type": {
                "key": {
                    "href": "https://eu.api.blizzard.com/data/wow/modified-crafting/reagent-slot-type/49?namespace=static-10.0.5_47621-eu"
                },
                "id": 49
            },
            "display_order": 0
        }
    ]
}