{
    "_links": {
        "self": {
            "href": "https://eu.api.blizzard.com/data/wow/recipe/9936?namespace=static-10.0.5_47621-eu"
        }
    },
    "id": 9936,
    "name": "Stonescale Oil",
    "media": {
        "key": {
            "href": "https://eu.api.blizzard.com/data/wow/media/recipe/9936?namespace=static-10.0.5_47621-eu"
        },
        "id": 9936
    },
    "crafted_item": {
        "key": {
            "href": "https://eu.api.blizzard.com/data/wow/item/13423?namespace=static-10.0.5_47621-eu"
        },
        "name": "Stonescale Oil",
        "id": 13423
    },
    "reagents": [
        {
            "reagent": {
                "key": {
                    "href": "https://eu.api.blizzard.com/data/wow/item/13422?namespace=static-10.0.5_47621-eu"
                },
                "name": "Stonescale Eel",
                "id": 13422
            },
            "quantity": 1
        }
    ],
    "crafted_quantity": {
        "value": 1.0
    }
}