{
    "_links": {
        "self": {
            "href": "https://eu.api.blizzard.com/data/wow/recipe/36560?namespace=static-10.0.5_47621-eu"
        }
    },
    "id": 36560,
    "name": "Vigilance Perch",
    "description": "Craft Vigilance Perch.",
    "media": {
        "key": {
            "href": "https://eu.api.blizzard.com/data/wow/media/recipe/36560?namespace=static-10.0.5_47621-eu"
        },
        "id": 36560
    },
    "crafted_item": {
        "key": {
            "href": "https://eu.api.blizzard.com/data/wow/item/146668?namespace=static-10.0.5_47621-eu"
        },
        "name": "Vigilance Perch",
        "id": 146668
    },
    "reagents": [
        {
            "reagent": {
                "key": {
                    "href": "https://eu.api.blizzard.com/data/wow/item/146713?namespace=static-10.0.5_47621-eu"
                },
                "name": "Prime Wardenscale",
                "id": 146713
            },
            "quantity": 1
        },
        {
            "reagent": {
                "key": {
                    "href": "https://eu.api.blizzard.com/data/wow/item/146659?namespace=static-10.0.5_47621-eu"
                },
                "name": "Nethershard Essence",
                "id": 146659
            },
            "quantity": 1
        },
        {
            "reagent": {
                "key": {
                    "href": "https://eu.api.blizzard.com/data/wow/item/124124?namespace=static-10.0.5_47621-eu"
                },
                "name": "Blood of Sargeras",
                "id": 124124
            },
            "quantity": 65
        },
        {
            "reagent": {
                "key": {
                    "href": "https://eu.api.blizzard.com/data/wow/item/124115?namespace=static-10.0.5_47621-eu"
                },
                "name": "Stormscale",
                "id": 124115
            },
            "quantity": 250
        }
    ],
    "crafted_quantity": {
        "value": 1.0
    }
}