{
    "_links": {
        "self": {
            "href": "https://eu.api.blizzard.com/data/wow/recipe/36151?namespace=static-10.0.5_47621-eu"
        }
    },
    "id": 36151,
    "name": "Heavy Scale Pants",
    "media": {
        "key": {
            "href": "https://eu.api.blizzard.com/data/wow/media/recipe/36151?namespace=static-10.0.5_47621-eu"
        },
        "id": 36151
    },
    "crafted_item": {
        "key": {
            "href": "https://eu.api.blizzard.com/data/wow/item/132532?namespace=static-10.0.5_47621-eu"
        },
        "name": "Heavy Scale Pants",
        "id": 132532
    },
    "reagents": [
        {
            "reagent": {
                "key": {
                    "href": "https://eu.api.blizzard.com/data/wow/item/4234?namespace=static-10.0.5_47621-eu"
                },
                "name": "Heavy Leather",
                "id": 4234
            },
            "quantity": 10
        },
        {
            "reagent": {
                "key": {
                    "href": "https://eu.api.blizzard.com/data/wow/item/2325?namespace=static-10.0.5_47621-eu"
                },
                "name": "Black Dye",
                "id": 2325
            },
            "quantity": 1
        },
        {
            "reagent": {
                "key": {
                    "href": "https://eu.api.blizzard.com/data/wow/item/2321?namespace=static-10.0.5_47621-eu"
                },
                "name": "Fine Thread",
                "id": 2321
            },
            "quantity": 2
        }
    ],
    "crafted_quantity": {
        "value": 1.0
    },
    "modified_crafting_slots": [
        {
            "slot_type": {
                "key": {
                    "href": "https://eu.api.blizzard.com/data/wow/modified-crafting/reagent-slot-type/48?namespace=static-10.0.5_47621-eu"
                },
                "id": 48
            },
            "display_order": 0
        }
    ]
}