{
    "_links": {
        "self": {
            "href": "https://eu.api.blizzard.com/data/wow/item/127261?namespace=static-10.0.5_47621-eu"
        }
    },
    "id": 127261,
    "name": "Pinkish Leyfeather",
    "quality": {
        "type": "COMMON",
        "name": "Common"
    },
    "level": 1,
    "required_level": 0,
    "media": {
        "key": {
            "href": "https://eu.api.blizzard.com/data/wow/media/item/127261?namespace=static-10.0.5_47621-eu"
        },
        "id": 127261
    },
    "item_class": {
        "key": {
            "href": "https://eu.api.blizzard.com/data/wow/item-class/12?namespace=static-10.0.5_47621-eu"
        },
        "name": "Quest",
        "id": 12
    },
    "item_subclass": {
        "key": {
            "href": "https://eu.api.blizzard.com/data/wow/item-class/12/item-subclass/0?namespace=static-10.0.5_47621-eu"
        },
        "name": "Quest",
        "id": 0
    },
    "inventory_type": {
        "type": "NON_EQUIP",
        "name": "Non-equippable"
    },
    "purchase_price": 0,
    "sell_price": 0,
    "max_count": 0,
    "is_equippable": false,
    "is_stackable": true,
    "description": "Only a very specific part of the hippogryph grows pink feathers.",
    "preview_item": {
        "item": {
            "key": {
                "href": "https://eu.api.blizzard.com/data/wow/item/127261?namespace=static-10.0.5_47621-eu"
            },
            "id": 127261
        },
        "quality": {
            "type": "COMMON",
            "name": "Common"
        },
        "name": "Pinkish Leyfeather",
        "media": {
            "key": {
                "href": "https://eu.api.blizzard.com/data/wow/media/item/127261?namespace=static-10.0.5_47621-eu"
            },
            "id": 127261
        },
        "item_class": {
            "key": {
                "href": "https://eu.api.blizzard.com/data/wow/item-class/12?namespace=static-10.0.5_47621-eu"
            },
            "name": "Quest",
            "id": 12
        },
        "item_subclass": {
            "key": {
                "href": "https://eu.api.blizzard.com/data/wow/item-class/12/item-subclass/0?namespace=static-10.0.5_47621-eu"
            },
            "name": "Quest",
            "id": 0
        },
        "inventory_type": {
            "type": "NON_EQUIP",
            "name": "Non-equippable"
        },
        "binding": {
            "type": "QUEST",
            "name": "Quest Item"
        },
        "description": "Only a very specific part of the hippogryph grows pink feathers.",
        "is_subclass_hidden": true
    },
    "purchase_quantity": 1
}