{
    "_links": {
        "self": {
            "href": "https://eu.api.blizzard.com/data/wow/item/138345?namespace=static-10.0.5_47621-eu"
        }
    },
    "id": 138345,
    "name": "Leggings of Shackled Elements",
    "quality": {
        "type": "EPIC",
        "name": "Epic"
    },
    "level": 50,
    "required_level": 45,
    "media": {
        "key": {
            "href": "https://eu.api.blizzard.com/data/wow/media/item/138345?namespace=static-10.0.5_47621-eu"
        },
        "id": 138345
    },
    "item_class": {
        "key": {
            "href": "https://eu.api.blizzard.com/data/wow/item-class/4?namespace=static-10.0.5_47621-eu"
        },
        "name": "Armor",
        "id": 4
    },
    "item_subclass": {
        "key": {
            "href": "https://eu.api.blizzard.com/data/wow/item-class/4/item-subclass/3?namespace=static-10.0.5_47621-eu"
        },
        "name": "Mail",
        "id": 3
    },
    "inventory_type": {
        "type": "LEGS",
        "name": "Legs"
    },
    "purchase_price": 2953368,
    "sell_price": 590673,
    "max_count": 0,
    "is_equippable": true,
    "is_stackable": false,
    "preview_item": {
        "item": {
            "key": {
                "href": "https://eu.api.blizzard.com/data/wow/item/138345?namespace=static-10.0.5_47621-eu"
            },
            "id": 138345
        },
        "quality": {
            "type": "EPIC",
            "name": "Epic"
        },
        "name": "Leggings of Shackled Elements",
        "media": {
            "key": {
                "href": "https://eu.api.blizzard.com/data/wow/media/item/138345?namespace=static-10.0.5_47621-eu"
            },
            "id": 138345
        },
        "item_class": {
            "key": {
                "href": "https://eu.api.blizzard.com/data/wow/item-class/4?namespace=static-10.0.5_47621-eu"
            },
            "name": "Armor",
            "id": 4
        },
        "item_subclass": {
            "key": {
                "href": "https://eu.api.blizzard.com/data/wow/item-class/4/item-subclass/3?namespace=static-10.0.5_47621-eu"
            },
            "name": "Mail",
            "id": 3
        },
        "inventory_type": {
            "type": "LEGS",
            "name": "Legs"
        },
        "binding": {
            "type": "ON_ACQUIRE",
            "name": "Binds when picked up"
        },
        "armor": {
            "value": 14,
            "display": {
                "display_string": "14 Armor",
                "color": {
                    "r": 255,
                    "g": 255,
                    "b": 255,
                    "a": 1.0
                }
            }
        },
        "stats": [
            {
                "type": {
                    "type": "INTELLECT",
                    "name": "Intellect"
                },
                "value": 6,
                "display": {
                    "display_string": "+6 Intellect",
                    "color": {
                        "r": 255,
                        "g": 255,
                        "b": 255,
                        "a": 1.0
                    }
                }
            },
            {
                "type": {
                    "type": "AGILITY",
                    "name": "Agility"
                },
                "value": 6,
                "is_negated": true,
                "display": {
                    "display_string": "+6 Agility",
                    "color": {
                        "r": 128,
                        "g": 128,
                        "b": 128,
                        "a": 1.0
                    }
                }
            },
            {
                "type": {
                    "type": "STAMINA",
                    "name": "Stamina"
                },
                "value": 10,
                "display": {
                    "display_string": "+10 Stamina",
                    "color": {
                        "r": 255,
                        "g": 255,
                        "b": 255,
                        "a": 1.0
                    }
                }
            },
            {
                "type": {
                    "type": "VERSATILITY",
                    "name": "Versatility"
                },
                "value": 5,
                "is_equip_bonus": true,
                "display": {
                    "display_string": "+5 Versatility",
                    "color": {
                        "r": 0,
                        "g": 255,
                        "b": 0,
                        "a": 1.0
                    }
                }
            },
            {
                "type": {
                    "type": "MASTERY_RATING",
                    "name": "Mastery"
                },
                "value": 8,
                "is_equip_bonus": true,
                "display": {
                    "display_string": "+8 Mastery",
                    "color": {
                        "r": 0,
                        "g": 255,
                        "b": 0,
                        "a": 1.0
                    }
                }
            }
        ],
        "sell_price": {
            "value": 2172,
            "display_strings": {
                "header": "Sell Price:",
                "gold": "0",
                "silver": "21",
                "copper": "72"
            }
        },
        "requirements": {
            "level": {
                "value": 45,
                "display_string": "Requires Level 45"
            },
            "playable_classes": {
                "links": [
                    {
                        "key": {
                            "href": "https://eu.api.blizzard.com/data/wow/playable-class/7?namespace=static-10.0.5_47621-eu"
                        },
                        "name": "Shaman",
                        "id": 7
                    }
                ],
                "display_string": "Classes: Shaman"
            }
        },
        "set": {
            "item_set": {
                "key": {
                    "href": "https://eu.api.blizzard.com/data/wow/item-set/1290?namespace=static-10.0.5_47621-eu"
                },
                "name": "Regalia of Shackled Elements",
                "id": 1290
            },
            "items": [
                {
                    "item": {
                        "key": {
                            "href": "https://eu.api.blizzard.com/data/wow/item/138341?namespace=static-10.0.5_47621-eu"
                        },
                        "name": "Gauntlets of Shackled Elements",
                        "id": 138341
                    }
                },
                {
                    "item": {
                        "key": {
                            "href": "https://eu.api.blizzard.com/data/wow/item/138343?namespace=static-10.0.5_47621-eu"
                        },
                        "name": "Helm of Shackled Elements",
                        "id": 138343
                    }
                },
                {
                    "item": {
                        "key": {
                            "href": "https://eu.api.blizzard.com/data/wow/item/138345?namespace=static-10.0.5_47621-eu"
                        },
                        "name": "Leggings of Shackled Elements",
                        "id": 138345
                    }
                },
                {
                    "item": {
                        "key": {
                            "href": "https://eu.api.blizzard.com/data/wow/item/138346?namespace=static-10.0.5_47621-eu"
                        },
                        "name": "Raiment of Shackled Elements",
                        "id": 138346
                    }
                },
                {
                    "item": {
                        "key": {
                            "href": "https://eu.api.blizzard.com/data/wow/item/138348?namespace=static-10.0.5_47621-eu"
                        },
                        "name": "Pauldrons of Shackled Elements",
                        "id": 138348
                    }
                },
                {
                    "item": {
                        "key": {
                            "href": "https://eu.api.blizzard.com/data/wow/item/138372?namespace=static-10.0.5_47621-eu"
                        },
                        "name": "Cloak of Shackled Elements",
                        "id": 138372
                    }
                }
            ],
            "legacy": "Legacy Set: Bonus is inactive",
            "display_string": "Regalia of Shackled Elements (0/6)"
        },
        "level": {
            "value": 50,
            "display_string": "Item Level 50"
        },
        "durability": {
            "value": 120,
            "display_string": "Durability 120 / 120"
        }
    },
    "purchase_quantity": 1
}