{
    "_links": {
        "self": {
            "href": "https://eu.api.blizzard.com/data/wow/item/170137?namespace=static-10.0.5_47621-eu"
        }
    },
    "id": 170137,
    "name": "Azerite-Infused Crystal Flayer",
    "quality": {
        "type": "EPIC",
        "name": "Epic"
    },
    "level": 60,
    "required_level": 50,
    "media": {
        "key": {
            "href": "https://eu.api.blizzard.com/data/wow/media/item/170137?namespace=static-10.0.5_47621-eu"
        },
        "id": 170137
    },
    "item_class": {
        "key": {
            "href": "https://eu.api.blizzard.com/data/wow/item-class/2?namespace=static-10.0.5_47621-eu"
        },
        "name": "Weapon",
        "id": 2
    },
    "item_subclass": {
        "key": {
            "href": "https://eu.api.blizzard.com/data/wow/item-class/2/item-subclass/15?namespace=static-10.0.5_47621-eu"
        },
        "name": "Dagger",
        "id": 15
    },
    "inventory_type": {
        "type": "WEAPON",
        "name": "One-Hand"
    },
    "purchase_price": 5366562,
    "sell_price": 1073312,
    "max_count": 0,
    "is_equippable": true,
    "is_stackable": false,
    "preview_item": {
        "item": {
            "key": {
                "href": "https://eu.api.blizzard.com/data/wow/item/170137?namespace=static-10.0.5_47621-eu"
            },
            "id": 170137
        },
        "context": 0,
        "bonus_list": [
            1478,
            4786
        ],
        "quality": {
            "type": "EPIC",
            "name": "Epic"
        },
        "name": "Azerite-Infused Crystal Flayer",
        "media": {
            "key": {
                "href": "https://eu.api.blizzard.com/data/wow/media/item/170137?namespace=static-10.0.5_47621-eu"
            },
            "id": 170137
        },
        "item_class": {
            "key": {
                "href": "https://eu.api.blizzard.com/data/wow/item-class/2?namespace=static-10.0.5_47621-eu"
            },
            "name": "Weapon",
            "id": 2
        },
        "item_subclass": {
            "key": {
                "href": "https://eu.api.blizzard.com/data/wow/item-class/2/item-subclass/15?namespace=static-10.0.5_47621-eu"
            },
            "name": "Dagger",
            "id": 15
        },
        "inventory_type": {
            "type": "WEAPON",
            "name": "One-Hand"
        },
        "binding": {
            "type": "ON_ACQUIRE",
            "name": "Binds when picked up"
        },
        "weapon": {
            "damage": {
                "min_value": 7,
                "max_value": 12,
                "display_string": "7 - 12 Damage",
                "damage_class": {
                    "type": "PHYSICAL",
                    "name": "Physical"
                }
            },
            "attack_speed": {
                "value": 1800,
                "display_string": "Speed 1.80"
            },
            "dps": {
                "value": 5.2777777,
                "display_string": "(5.3 damage per second)"
            }
        },
        "stats": [
            {
                "type": {
                    "type": "AGILITY",
                    "name": "Agility"
                },
                "value": 5,
                "is_negated": true,
                "display": {
                    "display_string": "+5 Agility",
                    "color": {
                        "r": 128,
                        "g": 128,
                        "b": 128,
                        "a": 1.0
                    }
                }
            },
            {
                "type": {
                    "type": "STAMINA",
                    "name": "Stamina"
                },
                "value": 7,
                "display": {
                    "display_string": "+7 Stamina",
                    "color": {
                        "r": 255,
                        "g": 255,
                        "b": 255,
                        "a": 1.0
                    }
                }
            },
            {
                "type": {
                    "type": "CRIT_RATING",
                    "name": "Critical Strike"
                },
                "value": 6,
                "is_equip_bonus": true,
                "display": {
                    "display_string": "+6 Critical Strike",
                    "color": {
                        "r": 0,
                        "g": 255,
                        "b": 0,
                        "a": 1.0
                    }
                }
            },
            {
                "type": {
                    "type": "HASTE_RATING",
                    "name": "Haste"
                },
                "value": 4,
                "is_equip_bonus": true,
                "display": {
                    "display_string": "+4 Haste",
                    "color": {
                        "r": 0,
                        "g": 255,
                        "b": 0,
                        "a": 1.0
                    }
                }
            }
        ],
        "sell_price": {
            "value": 8152,
            "display_strings": {
                "header": "Sell Price:",
                "gold": "0",
                "silver": "81",
                "copper": "52"
            }
        },
        "requirements": {
            "level": {
                "value": 50,
                "display_string": "Requires Level 50"
            }
        },
        "level": {
            "value": 66,
            "display_string": "Item Level 66"
        },
        "durability": {
            "value": 80,
            "display_string": "Durability 80 / 80"
        }
    },
    "purchase_quantity": 1
}