{
    "_links": {
        "self": {
            "href": "https://eu.api.blizzard.com/data/wow/item/182211?namespace=static-10.0.5_47621-eu"
        }
    },
    "id": 182211,
    "name": "Stone Brick",
    "quality": {
        "type": "COMMON",
        "name": "Common"
    },
    "level": 1,
    "required_level": 0,
    "media": {
        "key": {
            "href": "https://eu.api.blizzard.com/data/wow/media/item/182211?namespace=static-10.0.5_47621-eu"
        },
        "id": 182211
    },
    "item_class": {
        "key": {
            "href": "https://eu.api.blizzard.com/data/wow/item-class/15?namespace=static-10.0.5_47621-eu"
        },
        "name": "Miscellaneous",
        "id": 15
    },
    "item_subclass": {
        "key": {
            "href": "https://eu.api.blizzard.com/data/wow/item-class/15/item-subclass/4?namespace=static-10.0.5_47621-eu"
        },
        "name": "Other",
        "id": 4
    },
    "inventory_type": {
        "type": "NON_EQUIP",
        "name": "Non-equippable"
    },
    "purchase_price": 4,
    "sell_price": 1,
    "max_count": 10,
    "is_equippable": false,
    "is_stackable": true,
    "description": "Scuffs can use this to create a statue to honor you (+|CFF1b8729Decadent|R) or others (|CFF1b8729+Humble|R).",
    "preview_item": {
        "item": {
            "key": {
                "href": "https://eu.api.blizzard.com/data/wow/item/182211?namespace=static-10.0.5_47621-eu"
            },
            "id": 182211
        },
        "quality": {
            "type": "COMMON",
            "name": "Common"
        },
        "name": "Stone Brick",
        "media": {
            "key": {
                "href": "https://eu.api.blizzard.com/data/wow/media/item/182211?namespace=static-10.0.5_47621-eu"
            },
            "id": 182211
        },
        "item_class": {
            "key": {
                "href": "https://eu.api.blizzard.com/data/wow/item-class/15?namespace=static-10.0.5_47621-eu"
            },
            "name": "Miscellaneous",
            "id": 15
        },
        "item_subclass": {
            "key": {
                "href": "https://eu.api.blizzard.com/data/wow/item-class/15/item-subclass/4?namespace=static-10.0.5_47621-eu"
            },
            "name": "Other",
            "id": 4
        },
        "inventory_type": {
            "type": "NON_EQUIP",
            "name": "Non-equippable"
        },
        "binding": {
            "type": "ON_ACQUIRE",
            "name": "Binds when picked up"
        },
        "unique_equipped": "Unique (10)",
        "sell_price": {
            "value": 1,
            "display_strings": {
                "header": "Sell Price:",
                "gold": "0",
                "silver": "0",
                "copper": "1"
            }
        },
        "description": "Scuffs can use this to create a statue to honor you (+|CFF1b8729Decadent|R) or others (|CFF1b8729+Humble|R).",
        "is_subclass_hidden": true,
        "name_description": {
            "display_string": "Ember Court",
            "color": {
                "r": 136,
                "g": 170,
                "b": 255,
                "a": 1.0
            }
        }
    },
    "purchase_quantity": 1
}