{
    "_links": {
        "self": {
            "href": "https://eu.api.blizzard.com/data/wow/item/194085?namespace=static-10.0.5_47621-eu"
        }
    },
    "id": 194085,
    "name": "Proof of Might",
    "quality": {
        "type": "UNCOMMON",
        "name": "Uncommon"
    },
    "level": 1,
    "required_level": 1,
    "media": {
        "key": {
            "href": "https://eu.api.blizzard.com/data/wow/media/item/194085?namespace=static-10.0.5_47621-eu"
        },
        "id": 194085
    },
    "item_class": {
        "key": {
            "href": "https://eu.api.blizzard.com/data/wow/item-class/12?namespace=static-10.0.5_47621-eu"
        },
        "name": "Quest",
        "id": 12
    },
    "item_subclass": {
        "key": {
            "href": "https://eu.api.blizzard.com/data/wow/item-class/12/item-subclass/0?namespace=static-10.0.5_47621-eu"
        },
        "name": "Quest",
        "id": 0
    },
    "inventory_type": {
        "type": "NON_EQUIP",
        "name": "Non-equippable"
    },
    "purchase_price": 0,
    "sell_price": 0,
    "max_count": 0,
    "is_equippable": false,
    "is_stackable": true,
    "description": "Return this token to the Shikaar Master of Might to prove your prowess in the grand hunt.",
    "preview_item": {
        "item": {
            "key": {
                "href": "https://eu.api.blizzard.com/data/wow/item/194085?namespace=static-10.0.5_47621-eu"
            },
            "id": 194085
        },
        "quality": {
            "type": "UNCOMMON",
            "name": "Uncommon"
        },
        "name": "Proof of Might",
        "media": {
            "key": {
                "href": "https://eu.api.blizzard.com/data/wow/media/item/194085?namespace=static-10.0.5_47621-eu"
            },
            "id": 194085
        },
        "item_class": {
            "key": {
                "href": "https://eu.api.blizzard.com/data/wow/item-class/12?namespace=static-10.0.5_47621-eu"
            },
            "name": "Quest",
            "id": 12
        },
        "item_subclass": {
            "key": {
                "href": "https://eu.api.blizzard.com/data/wow/item-class/12/item-subclass/0?namespace=static-10.0.5_47621-eu"
            },
            "name": "Quest",
            "id": 0
        },
        "inventory_type": {
            "type": "NON_EQUIP",
            "name": "Non-equippable"
        },
        "binding": {
            "type": "ON_ACQUIRE",
            "name": "Binds when picked up"
        },
        "description": "Return this token to the Shikaar Master of Might to prove your prowess in the grand hunt.",
        "is_subclass_hidden": true,
        "name_description": {
            "display_string": "Hunting Party",
            "color": {
                "r": 102,
                "g": 187,
                "b": 255,
                "a": 1.0
            }
        }
    },
    "purchase_quantity": 10
}