{
    "_links": {
        "self": {
            "href": "https://eu.api.blizzard.com/data/wow/item/19861?namespace=static-10.0.5_47621-eu"
        }
    },
    "id": 19861,
    "name": "Touch of Chaos",
    "quality": {
        "type": "EPIC",
        "name": "Epic"
    },
    "level": 29,
    "required_level": 25,
    "media": {
        "key": {
            "href": "https://eu.api.blizzard.com/data/wow/media/item/19861?namespace=static-10.0.5_47621-eu"
        },
        "id": 19861
    },
    "item_class": {
        "key": {
            "href": "https://eu.api.blizzard.com/data/wow/item-class/2?namespace=static-10.0.5_47621-eu"
        },
        "name": "Weapon",
        "id": 2
    },
    "item_subclass": {
        "key": {
            "href": "https://eu.api.blizzard.com/data/wow/item-class/2/item-subclass/19?namespace=static-10.0.5_47621-eu"
        },
        "name": "Wand",
        "id": 19
    },
    "inventory_type": {
        "type": "RANGEDRIGHT",
        "name": "Ranged"
    },
    "purchase_price": 584034,
    "sell_price": 116806,
    "max_count": 0,
    "is_equippable": true,
    "is_stackable": false,
    "preview_item": {
        "item": {
            "key": {
                "href": "https://eu.api.blizzard.com/data/wow/item/19861?namespace=static-10.0.5_47621-eu"
            },
            "id": 19861
        },
        "quality": {
            "type": "EPIC",
            "name": "Epic"
        },
        "name": "Touch of Chaos",
        "media": {
            "key": {
                "href": "https://eu.api.blizzard.com/data/wow/media/item/19861?namespace=static-10.0.5_47621-eu"
            },
            "id": 19861
        },
        "item_class": {
            "key": {
                "href": "https://eu.api.blizzard.com/data/wow/item-class/2?namespace=static-10.0.5_47621-eu"
            },
            "name": "Weapon",
            "id": 2
        },
        "item_subclass": {
            "key": {
                "href": "https://eu.api.blizzard.com/data/wow/item-class/2/item-subclass/19?namespace=static-10.0.5_47621-eu"
            },
            "name": "Wand",
            "id": 19
        },
        "inventory_type": {
            "type": "RANGEDRIGHT",
            "name": "Ranged"
        },
        "binding": {
            "type": "ON_ACQUIRE",
            "name": "Binds when picked up"
        },
        "weapon": {
            "damage": {
                "min_value": 1,
                "max_value": 2,
                "display_string": "1 - 2 Shadow Damage",
                "damage_class": {
                    "type": "SHADOW",
                    "name": "Shadow"
                }
            },
            "attack_speed": {
                "value": 2000,
                "display_string": "Speed 2.00"
            },
            "dps": {
                "value": 0.75,
                "display_string": "(0.8 damage per second)"
            }
        },
        "stats": [
            {
                "type": {
                    "type": "INTELLECT",
                    "name": "Intellect"
                },
                "value": 10,
                "display": {
                    "display_string": "+10 Intellect",
                    "color": {
                        "r": 255,
                        "g": 255,
                        "b": 255,
                        "a": 1.0
                    }
                }
            },
            {
                "type": {
                    "type": "STAMINA",
                    "name": "Stamina"
                },
                "value": 2,
                "display": {
                    "display_string": "+2 Stamina",
                    "color": {
                        "r": 255,
                        "g": 255,
                        "b": 255,
                        "a": 1.0
                    }
                }
            }
        ],
        "sell_price": {
            "value": 558,
            "display_strings": {
                "header": "Sell Price:",
                "gold": "0",
                "silver": "5",
                "copper": "58"
            }
        },
        "requirements": {
            "level": {
                "value": 25,
                "display_string": "Requires Level 25"
            }
        },
        "level": {
            "value": 29,
            "display_string": "Item Level 29"
        },
        "durability": {
            "value": 110,
            "display_string": "Durability 110 / 110"
        }
    },
    "purchase_quantity": 1
}