{
    "_links": {
        "self": {
            "href": "https://eu.api.blizzard.com/data/wow/item/22076?namespace=static-10.0.5_47621-eu"
        }
    },
    "id": 22076,
    "name": "Deathmist Sandals",
    "quality": {
        "type": "EPIC",
        "name": "Epic"
    },
    "level": 29,
    "required_level": 0,
    "media": {
        "key": {
            "href": "https://eu.api.blizzard.com/data/wow/media/item/22076?namespace=static-10.0.5_47621-eu"
        },
        "id": 22076
    },
    "item_class": {
        "key": {
            "href": "https://eu.api.blizzard.com/data/wow/item-class/4?namespace=static-10.0.5_47621-eu"
        },
        "name": "Armor",
        "id": 4
    },
    "item_subclass": {
        "key": {
            "href": "https://eu.api.blizzard.com/data/wow/item-class/4/item-subclass/1?namespace=static-10.0.5_47621-eu"
        },
        "name": "Cloth",
        "id": 1
    },
    "inventory_type": {
        "type": "FEET",
        "name": "Feet"
    },
    "purchase_price": 176529,
    "sell_price": 35305,
    "max_count": 0,
    "is_equippable": true,
    "is_stackable": false,
    "preview_item": {
        "item": {
            "key": {
                "href": "https://eu.api.blizzard.com/data/wow/item/22076?namespace=static-10.0.5_47621-eu"
            },
            "id": 22076
        },
        "quality": {
            "type": "EPIC",
            "name": "Epic"
        },
        "name": "Deathmist Sandals",
        "media": {
            "key": {
                "href": "https://eu.api.blizzard.com/data/wow/media/item/22076?namespace=static-10.0.5_47621-eu"
            },
            "id": 22076
        },
        "item_class": {
            "key": {
                "href": "https://eu.api.blizzard.com/data/wow/item-class/4?namespace=static-10.0.5_47621-eu"
            },
            "name": "Armor",
            "id": 4
        },
        "item_subclass": {
            "key": {
                "href": "https://eu.api.blizzard.com/data/wow/item-class/4/item-subclass/1?namespace=static-10.0.5_47621-eu"
            },
            "name": "Cloth",
            "id": 1
        },
        "inventory_type": {
            "type": "FEET",
            "name": "Feet"
        },
        "binding": {
            "type": "ON_ACQUIRE",
            "name": "Binds when picked up"
        },
        "armor": {
            "value": 2,
            "display": {
                "display_string": "2 Armor",
                "color": {
                    "r": 255,
                    "g": 255,
                    "b": 255,
                    "a": 1.0
                }
            }
        },
        "stats": [
            {
                "type": {
                    "type": "INTELLECT",
                    "name": "Intellect"
                },
                "value": 1,
                "display": {
                    "display_string": "+1 Intellect",
                    "color": {
                        "r": 255,
                        "g": 255,
                        "b": 255,
                        "a": 1.0
                    }
                }
            },
            {
                "type": {
                    "type": "STAMINA",
                    "name": "Stamina"
                },
                "value": 4,
                "display": {
                    "display_string": "+4 Stamina",
                    "color": {
                        "r": 255,
                        "g": 255,
                        "b": 255,
                        "a": 1.0
                    }
                }
            }
        ],
        "sell_price": {
            "value": 229,
            "display_strings": {
                "header": "Sell Price:",
                "gold": "0",
                "silver": "2",
                "copper": "29"
            }
        },
        "set": {
            "item_set": {
                "key": {
                    "href": "https://eu.api.blizzard.com/data/wow/item-set/518?namespace=static-10.0.5_47621-eu"
                },
                "name": "Deathmist Raiment",
                "id": 518
            },
            "items": [
                {
                    "item": {
                        "key": {
                            "href": "https://eu.api.blizzard.com/data/wow/item/22070?namespace=static-10.0.5_47621-eu"
                        },
                        "name": "Deathmist Belt",
                        "id": 22070
                    }
                },
                {
                    "item": {
                        "key": {
                            "href": "https://eu.api.blizzard.com/data/wow/item/22071?namespace=static-10.0.5_47621-eu"
                        },
                        "name": "Deathmist Bracers",
                        "id": 22071
                    }
                },
                {
                    "item": {
                        "key": {
                            "href": "https://eu.api.blizzard.com/data/wow/item/22072?namespace=static-10.0.5_47621-eu"
                        },
                        "name": "Deathmist Leggings",
                        "id": 22072
                    }
                },
                {
                    "item": {
                        "key": {
                            "href": "https://eu.api.blizzard.com/data/wow/item/22073?namespace=static-10.0.5_47621-eu"
                        },
                        "name": "Deathmist Mantle",
                        "id": 22073
                    }
                },
                {
                    "item": {
                        "key": {
                            "href": "https://eu.api.blizzard.com/data/wow/item/22074?namespace=static-10.0.5_47621-eu"
                        },
                        "name": "Deathmist Mask",
                        "id": 22074
                    }
                },
                {
                    "item": {
                        "key": {
                            "href": "https://eu.api.blizzard.com/data/wow/item/22075?namespace=static-10.0.5_47621-eu"
                        },
                        "name": "Deathmist Robe",
                        "id": 22075
                    }
                },
                {
                    "item": {
                        "key": {
                            "href": "https://eu.api.blizzard.com/data/wow/item/22076?namespace=static-10.0.5_47621-eu"
                        },
                        "name": "Deathmist Sandals",
                        "id": 22076
                    }
                },
                {
                    "item": {
                        "key": {
                            "href": "https://eu.api.blizzard.com/data/wow/item/22077?namespace=static-10.0.5_47621-eu"
                        },
                        "name": "Deathmist Wraps",
                        "id": 22077
                    }
                }
            ],
            "effects": [
                {
                    "display_string": "(2) Set: Reduces magical damage taken by 5%.",
                    "required_count": 2
                },
                {
                    "display_string": "(4) Set: When struck in combat has a chance of causing the attacker to flee in terror for 2 seconds.",
                    "required_count": 4
                },
                {
                    "display_string": "(6) Set: Increases Intellect by 9.",
                    "required_count": 6
                },
                {
                    "display_string": "(8) Set: +14 Armor.",
                    "required_count": 8
                }
            ],
            "display_string": "Deathmist Raiment (0/8)"
        },
        "level": {
            "value": 29,
            "display_string": "Item Level 29"
        },
        "durability": {
            "value": 80,
            "display_string": "Durability 80 / 80"
        }
    },
    "purchase_quantity": 1
}