{
    "_links": {
        "self": {
            "href": "https://eu.api.blizzard.com/data/wow/item/58949?namespace=static-10.0.5_47621-eu"
        }
    },
    "id": 58949,
    "name": "Stag Eye",
    "quality": {
        "type": "COMMON",
        "name": "Common"
    },
    "level": 1,
    "required_level": 0,
    "media": {
        "key": {
            "href": "https://eu.api.blizzard.com/data/wow/media/item/58949?namespace=static-10.0.5_47621-eu"
        },
        "id": 58949
    },
    "item_class": {
        "key": {
            "href": "https://eu.api.blizzard.com/data/wow/item-class/12?namespace=static-10.0.5_47621-eu"
        },
        "name": "Quest",
        "id": 12
    },
    "item_subclass": {
        "key": {
            "href": "https://eu.api.blizzard.com/data/wow/item-class/12/item-subclass/0?namespace=static-10.0.5_47621-eu"
        },
        "name": "Quest",
        "id": 0
    },
    "inventory_type": {
        "type": "NON_EQUIP",
        "name": "Non-equippable"
    },
    "purchase_price": 0,
    "sell_price": 0,
    "max_count": 0,
    "is_equippable": false,
    "is_stackable": true,
    "description": "The eye still flinches occasionaly.",
    "preview_item": {
        "item": {
            "key": {
                "href": "https://eu.api.blizzard.com/data/wow/item/58949?namespace=static-10.0.5_47621-eu"
            },
            "id": 58949
        },
        "quality": {
            "type": "COMMON",
            "name": "Common"
        },
        "name": "Stag Eye",
        "media": {
            "key": {
                "href": "https://eu.api.blizzard.com/data/wow/media/item/58949?namespace=static-10.0.5_47621-eu"
            },
            "id": 58949
        },
        "item_class": {
            "key": {
                "href": "https://eu.api.blizzard.com/data/wow/item-class/12?namespace=static-10.0.5_47621-eu"
            },
            "name": "Quest",
            "id": 12
        },
        "item_subclass": {
            "key": {
                "href": "https://eu.api.blizzard.com/data/wow/item-class/12/item-subclass/0?namespace=static-10.0.5_47621-eu"
            },
            "name": "Quest",
            "id": 0
        },
        "inventory_type": {
            "type": "NON_EQUIP",
            "name": "Non-equippable"
        },
        "binding": {
            "type": "QUEST",
            "name": "Quest Item"
        },
        "spells": [
            {
                "spell": {
                    "key": {
                        "href": "https://eu.api.blizzard.com/data/wow/spell/80868?namespace=static-10.0.5_47621-eu"
                    },
                    "name": "Stag Eye Bait",
                    "id": 80868
                },
                "description": "Use: Attaches a Stag Eye to your fishing pole for 10 min."
            }
        ],
        "description": "The eye still flinches occasionaly.",
        "is_subclass_hidden": true
    },
    "purchase_quantity": 5
}