{
    "_links": {
        "self": {
            "href": "https://eu.api.blizzard.com/data/wow/recipe/40153?namespace=static-10.0.5_47621-eu"
        }
    },
    "id": 40153,
    "name": "Sanguinated Reconstruction",
    "description": "Convert one Breath of Bwonsamdi into one Sanguicell.",
    "media": {
        "key": {
            "href": "https://eu.api.blizzard.com/data/wow/media/recipe/40153?namespace=static-10.0.5_47621-eu"
        },
        "id": 40153
    },
    "crafted_item": {
        "key": {
            "href": "https://eu.api.blizzard.com/data/wow/item/162461?namespace=static-10.0.5_47621-eu"
        },
        "name": "Sanguicell",
        "id": 162461
    },
    "reagents": [
        {
            "reagent": {
                "key": {
                    "href": "https://eu.api.blizzard.com/data/wow/item/165703?namespace=static-10.0.5_47621-eu"
                },
                "name": "Breath of Bwonsamdi",
                "id": 165703
            },
            "quantity": 1
        },
        {
            "reagent": {
                "key": {
                    "href": "https://eu.api.blizzard.com/data/wow/item/160298?namespace=static-10.0.5_47621-eu"
                },
                "name": "Durable Flux",
                "id": 160298
            },
            "quantity": 10
        }
    ],
    "crafted_quantity": {
        "value": 1.0
    }
}