{
    "_links": {
        "self": {
            "href": "https://eu.api.blizzard.com/data/wow/recipe/21217?namespace=static-10.0.5_47621-eu"
        }
    },
    "id": 21217,
    "name": "Ensorcelled Nerubian Breastplate",
    "media": {
        "key": {
            "href": "https://eu.api.blizzard.com/data/wow/media/recipe/21217?namespace=static-10.0.5_47621-eu"
        },
        "id": 21217
    },
    "alliance_crafted_item": {
        "key": {
            "href": "https://eu.api.blizzard.com/data/wow/item/47597?namespace=static-10.0.5_47621-eu"
        },
        "name": "Ensorcelled Nerubian Breastplate",
        "id": 47597
    },
    "horde_crafted_item": {
        "key": {
            "href": "https://eu.api.blizzard.com/data/wow/item/47598?namespace=static-10.0.5_47621-eu"
        },
        "name": "Ensorcelled Nerubian Breastplate",
        "id": 47598
    },
    "reagents": [
        {
            "reagent": {
                "key": {
                    "href": "https://eu.api.blizzard.com/data/wow/item/38558?namespace=static-10.0.5_47621-eu"
                },
                "name": "Nerubian Chitin",
                "id": 38558
            },
            "quantity": 40
        },
        {
            "reagent": {
                "key": {
                    "href": "https://eu.api.blizzard.com/data/wow/item/35623?namespace=static-10.0.5_47621-eu"
                },
                "name": "Eternal Air",
                "id": 35623
            },
            "quantity": 8
        },
        {
            "reagent": {
                "key": {
                    "href": "https://eu.api.blizzard.com/data/wow/item/34055?namespace=static-10.0.5_47621-eu"
                },
                "name": "Greater Cosmic Essence",
                "id": 34055
            },
            "quantity": 8
        },
        {
            "reagent": {
                "key": {
                    "href": "https://eu.api.blizzard.com/data/wow/item/44128?namespace=static-10.0.5_47621-eu"
                },
                "name": "Arctic Fur",
                "id": 44128
            },
            "quantity": 8
        },
        {
            "reagent": {
                "key": {
                    "href": "https://eu.api.blizzard.com/data/wow/item/47556?namespace=static-10.0.5_47621-eu"
                },
                "name": "Crusader Orb",
                "id": 47556
            },
            "quantity": 8
        }
    ],
    "crafted_quantity": {
        "value": 1.0
    }
}