{
    "_links": {
        "self": {
            "href": "https://eu.api.blizzard.com/data/wow/recipe/16117?namespace=static-10.0.5_47621-eu"
        }
    },
    "id": 16117,
    "name": "Superior Dodge",
    "description": "Permanently enchant a cloak to increase dodge by 4. Cannot be applied to items higher than level 50.",
    "media": {
        "key": {
            "href": "https://eu.api.blizzard.com/data/wow/media/recipe/16117?namespace=static-10.0.5_47621-eu"
        },
        "id": 16117
    },
    "crafted_quantity": {
        "value": 1.0
    }
}