{
    "_links": {
        "self": {
            "href": "https://eu.api.blizzard.com/data/wow/recipe/47961?namespace=static-10.0.5_47621-eu"
        }
    },
    "id": 47961,
    "name": "Iridescent Ore",
    "description": "Chunks of Iridescent Ore are often found by diligent miners as they scour the Dragon Isles. Taking a moment to study these will grant further knowledge toward your mining specializations.\r\n\r\nYou may discover 6 more sample(s) this week.",
    "media": {
        "key": {
            "href": "https://eu.api.blizzard.com/data/wow/media/recipe/47961?namespace=static-10.0.5_47621-eu"
        },
        "id": 47961
    }
}